{
	"name": "testEV",
	"events": [
		{
			"eventType": "include",
			"includeSheet": "uiEV"
		},
		{
			"eventType": "comment",
			"text": "on start of layout, activate the main section",
			"text-color": [
				0,
				0,
				0,
				1
			],
			"background-color": [
				0.6431372549019608,
				0.8470588235294118,
				0.8745098039215686,
				1
			]
		},
		{
			"eventType": "block",
			"conditions": [
				{
					"id": "on-start-of-layout",
					"objectClass": "System",
					"sid": 945432562778651
				}
			],
			"actions": [
				{
					"callFunction": "uiEnableSection",
					"sid": 905186969619809,
					"parameters": [
						"\"main\""
					]
				},
				{
					"id": "set-layer-visible",
					"objectClass": "System",
					"sid": 545677174326158,
					"parameters": {
						"layer": "\"quit confirm\"",
						"visibility": "invisible"
					}
				},
				{
					"id": "set-layer-visible",
					"objectClass": "System",
					"sid": 873553509964271,
					"parameters": {
						"layer": "\"settings\"",
						"visibility": "invisible"
					}
				}
			],
			"sid": 800095717628148
		},
		{
			"eventType": "group",
			"disabled": false,
			"title": "main",
			"description": "",
			"isActiveOnStart": true,
			"children": [
				{
					"eventType": "comment",
					"text": "when ANY button that has the section \"main\" is selected...",
					"text-color": [
						0,
						0,
						0,
						1
					],
					"background-color": [
						0.6431372549019608,
						0.8470588235294118,
						0.8745098039215686,
						1
					]
				},
				{
					"aceType": "action",
					"aceName": "uiSelect",
					"objectClass": "uiMainButton",
					"functionDescription": "overwrite the default behavior",
					"functionCategory": "ui",
					"functionReturnType": "none",
					"functionCopyPicked": false,
					"functionIsAsync": false,
					"functionParameters": [],
					"eventType": "custom-ace-block",
					"conditions": [],
					"actions": [
						{
							"type": "comment",
							"text": "call the default custom action (click this action to see that it's the one that belongs to the family)\nthis way, it'll do the default action of growing but ALSO whatever else we say",
							"text-color": [
								0,
								0,
								0,
								1
							],
							"background-color": [
								0.8745098039215686,
								0.8352941176470589,
								0.6431372549019608,
								1
							]
						},
						{
							"customAction": "uiSelect",
							"objectClass": "uiMainButton",
							"customActionObjectClass": "ui",
							"sid": 354804342021472
						},
						{
							"type": "comment",
							"text": "a little tilt effect",
							"text-color": [
								0,
								0,
								0,
								1
							],
							"background-color": [
								0.8745098039215686,
								0.8352941176470589,
								0.6431372549019608,
								1
							]
						},
						{
							"id": "set-angle",
							"objectClass": "uiMainButton",
							"sid": 225754369865291,
							"parameters": {
								"angle": "choose(-5, 5)"
							}
						},
						{
							"id": "tween-one-property",
							"objectClass": "uiMainButton",
							"sid": 856120774699574,
							"behaviorType": "Tween",
							"parameters": {
								"tags": "\"tilt\"",
								"property": "offsetAngle",
								"end-value": "0",
								"time": "0.1",
								"ease": "easeoutsine",
								"destroy-on-complete": "no",
								"loop": "no",
								"ping-pong": "no",
								"repeat-count": "1"
							}
						}
					],
					"sid": 974698822890559
				},
				{
					"eventType": "group",
					"disabled": false,
					"title": "main main",
					"description": "I know the name of this group is a bit strange, but I always put the name of the layout before putting the name of the UI section, which in this case... yeah.",
					"isActiveOnStart": true,
					"children": [
						{
							"eventType": "comment",
							"text": "quit selected",
							"text-color": [
								0,
								0,
								0,
								1
							],
							"background-color": [
								0.6431372549019608,
								0.8470588235294118,
								0.8745098039215686,
								1
							]
						},
						{
							"functionName": "select mainQuit",
							"functionDescription": "",
							"functionCategory": "select",
							"functionReturnType": "none",
							"functionCopyPicked": true,
							"functionIsAsync": false,
							"functionParameters": [],
							"eventType": "function-block",
							"conditions": [],
							"actions": [],
							"sid": 296968464749764,
							"children": [
								{
									"eventType": "block",
									"conditions": [],
									"actions": [
										{
											"type": "comment",
											"text": "disable the main menu, and enable the quit confirmation ui",
											"text-color": [
												0,
												0,
												0,
												1
											],
											"background-color": [
												0.8745098039215686,
												0.8352941176470589,
												0.6431372549019608,
												1
											]
										},
										{
											"callFunction": "uiEnableSection",
											"sid": 993432673397228,
											"parameters": [
												"\"mainQuit\""
											]
										},
										{
											"callFunction": "uiDisableSection",
											"sid": 274078826139542,
											"parameters": [
												"\"main\""
											]
										},
										{
											"type": "comment",
											"text": "make the quit menu move onto the screen",
											"text-color": [
												0,
												0,
												0,
												1
											],
											"background-color": [
												0.8745098039215686,
												0.8352941176470589,
												0.6431372549019608,
												1
											]
										},
										{
											"id": "set-layer-visible",
											"objectClass": "System",
											"sid": 755575869254307,
											"parameters": {
												"layer": "\"quit confirm\"",
												"visibility": "visible"
											}
										},
										{
											"id": "stop-tweens",
											"objectClass": "uiMainQuitBg",
											"sid": 874411357088735,
											"behaviorType": "Tween",
											"parameters": {
												"tags": "\"move\""
											}
										},
										{
											"id": "tween-one-property",
											"objectClass": "uiMainQuitBg",
											"sid": 553748785454300,
											"behaviorType": "Tween",
											"parameters": {
												"tags": "\"move\"",
												"property": "offsetY",
												"end-value": "Self.tY",
												"time": "0.2",
												"ease": "easeoutsine",
												"destroy-on-complete": "no",
												"loop": "no",
												"ping-pong": "no",
												"repeat-count": "1"
											}
										}
									],
									"sid": 897689551717139
								}
							]
						},
						{
							"eventType": "comment",
							"text": "settings",
							"text-color": [
								0,
								0,
								0,
								1
							],
							"background-color": [
								0.6431372549019608,
								0.8470588235294118,
								0.8745098039215686,
								1
							]
						},
						{
							"functionName": "select mainSettings",
							"functionDescription": "",
							"functionCategory": "select",
							"functionReturnType": "none",
							"functionCopyPicked": true,
							"functionIsAsync": false,
							"functionParameters": [],
							"eventType": "function-block",
							"conditions": [],
							"actions": [],
							"sid": 917958174478447,
							"children": [
								{
									"eventType": "block",
									"conditions": [],
									"actions": [
										{
											"callFunction": "uiEnableSection",
											"sid": 493391209093917,
											"parameters": [
												"\"mainSettings\""
											]
										},
										{
											"callFunction": "uiDisableSection",
											"sid": 514706532525314,
											"parameters": [
												"\"main\""
											]
										},
										{
											"type": "comment",
											"text": "make settings drop down",
											"text-color": [
												0,
												0,
												0,
												1
											],
											"background-color": [
												0.8745098039215686,
												0.8352941176470589,
												0.6431372549019608,
												1
											]
										},
										{
											"id": "set-layer-visible",
											"objectClass": "System",
											"sid": 243339950490133,
											"parameters": {
												"layer": "\"settings\"",
												"visibility": "visible"
											}
										},
										{
											"id": "stop-tweens",
											"objectClass": "uiMainSettingsBg",
											"sid": 916847032016759,
											"behaviorType": "Tween",
											"parameters": {
												"tags": "\"move\""
											}
										},
										{
											"id": "tween-one-property",
											"objectClass": "uiMainSettingsBg",
											"sid": 235467360857710,
											"behaviorType": "Tween",
											"parameters": {
												"tags": "\"move\"",
												"property": "offsetY",
												"end-value": "Self.tY",
												"time": "0.2",
												"ease": "easeoutsine",
												"destroy-on-complete": "no",
												"loop": "no",
												"ping-pong": "no",
												"repeat-count": "1"
											}
										}
									],
									"sid": 300464399961150
								}
							]
						}
					],
					"sid": 116526648231413,
					"text-color": [
						0,
						0,
						0,
						0
					],
					"background-color": [
						0.8392156862745098,
						0.8392156862745098,
						0.8392156862745098,
						1
					]
				},
				{
					"eventType": "group",
					"disabled": false,
					"title": "main quit",
					"description": "",
					"isActiveOnStart": true,
					"children": [
						{
							"eventType": "comment",
							"text": "when ANY button that has the section \"mainQuit\" is selected...",
							"text-color": [
								0,
								0,
								0,
								1
							],
							"background-color": [
								0.6431372549019608,
								0.8470588235294118,
								0.8745098039215686,
								1
							]
						},
						{
							"aceType": "action",
							"aceName": "uiSelect",
							"objectClass": "uiMainQuitButton",
							"functionDescription": "overwrite the default behavior",
							"functionCategory": "ui",
							"functionReturnType": "none",
							"functionCopyPicked": false,
							"functionIsAsync": false,
							"functionParameters": [],
							"eventType": "custom-ace-block",
							"conditions": [],
							"actions": [
								{
									"type": "comment",
									"text": "call the default custom action so that it'll do the default action of growing but ALSO whatever else we say",
									"text-color": [
										0,
										0,
										0,
										1
									],
									"background-color": [
										0.8745098039215686,
										0.8352941176470589,
										0.6431372549019608,
										1
									]
								},
								{
									"customAction": "uiSelect",
									"objectClass": "uiMainQuitButton",
									"customActionObjectClass": "ui",
									"sid": 391430290362098
								},
								{
									"type": "comment",
									"text": "a little tilt effect",
									"text-color": [
										0,
										0,
										0,
										1
									],
									"background-color": [
										0.8745098039215686,
										0.8352941176470589,
										0.6431372549019608,
										1
									]
								},
								{
									"id": "set-angle",
									"objectClass": "uiMainQuitButton",
									"sid": 426679167873826,
									"parameters": {
										"angle": "choose(-5, 5)"
									}
								},
								{
									"id": "tween-one-property",
									"objectClass": "uiMainQuitButton",
									"sid": 568137049276687,
									"behaviorType": "Tween",
									"parameters": {
										"tags": "\"tilt\"",
										"property": "offsetAngle",
										"end-value": "0",
										"time": "0.1",
										"ease": "easeoutsine",
										"destroy-on-complete": "no",
										"loop": "no",
										"ping-pong": "no",
										"repeat-count": "1"
									}
								}
							],
							"sid": 786158550210756
						},
						{
							"eventType": "comment",
							"text": "quit confirmed",
							"text-color": [
								0,
								0,
								0,
								1
							],
							"background-color": [
								0.6431372549019608,
								0.8470588235294118,
								0.8745098039215686,
								1
							]
						},
						{
							"functionName": "select mainQuitConfirm",
							"functionDescription": "",
							"functionCategory": "select",
							"functionReturnType": "none",
							"functionCopyPicked": true,
							"functionIsAsync": false,
							"functionParameters": [],
							"eventType": "function-block",
							"conditions": [],
							"actions": [],
							"sid": 282659452091309,
							"children": [
								{
									"eventType": "block",
									"conditions": [],
									"actions": [
										{
											"callFunction": "uiDisableAllSections",
											"sid": 610313680969286
										},
										{
											"id": "create-object",
											"objectClass": "System",
											"sid": 230914326958543,
											"parameters": {
												"object-to-create": "Particles",
												"layer": "\"quit confirm\"",
												"x": "ui.X",
												"y": "ui.Y",
												"create-hierarchy": false,
												"template-name": "\"\""
											}
										},
										{
											"id": "set-default-color",
											"objectClass": "ui",
											"sid": 574160268007345,
											"parameters": {
												"color": "rgbEx255(255, 0, 0)"
											}
										},
										{
											"id": "tween-one-property",
											"objectClass": "ui",
											"sid": 800079479170424,
											"behaviorType": "Tween",
											"parameters": {
												"tags": "\"flash\"",
												"property": "offsetColor",
												"end-value": "rgbEx255(255, 255, 255)",
												"time": "0.5",
												"ease": "easeoutsine",
												"destroy-on-complete": "no",
												"loop": "no",
												"ping-pong": "no",
												"repeat-count": "1"
											}
										},
										{
											"id": "wait-for-previous-actions",
											"objectClass": "System",
											"sid": 413297668791805
										},
										{
											"id": "close",
											"objectClass": "Browser",
											"sid": 278119950006880
										}
									],
									"sid": 946273662221958
								}
							]
						},
						{
							"eventType": "comment",
							"text": "quit cancelled",
							"text-color": [
								0,
								0,
								0,
								1
							],
							"background-color": [
								0.6431372549019608,
								0.8470588235294118,
								0.8745098039215686,
								1
							]
						},
						{
							"functionName": "select mainQuitCancel",
							"functionDescription": "",
							"functionCategory": "select",
							"functionReturnType": "none",
							"functionCopyPicked": true,
							"functionIsAsync": false,
							"functionParameters": [],
							"eventType": "function-block",
							"conditions": [],
							"actions": [],
							"sid": 835502629788125,
							"children": [
								{
									"eventType": "block",
									"conditions": [],
									"actions": [
										{
											"callFunction": "uiEnableSection",
											"sid": 292679896486895,
											"parameters": [
												"\"main\""
											]
										},
										{
											"callFunction": "uiDisableSection",
											"sid": 387979334557620,
											"parameters": [
												"\"mainQuit\""
											]
										},
										{
											"type": "comment",
											"text": "let the move menu fall away, but only make the layer invisible once it's gone",
											"text-color": [
												0,
												0,
												0,
												1
											],
											"background-color": [
												0.8745098039215686,
												0.8352941176470589,
												0.6431372549019608,
												1
											]
										},
										{
											"id": "stop-tweens",
											"objectClass": "uiMainQuitBg",
											"sid": 727764064773105,
											"behaviorType": "Tween",
											"parameters": {
												"tags": "\"move\""
											}
										},
										{
											"id": "tween-one-property",
											"objectClass": "uiMainQuitBg",
											"sid": 715262160336873,
											"behaviorType": "Tween",
											"parameters": {
												"tags": "\"move\"",
												"property": "offsetY",
												"end-value": "Self.oY",
												"time": "0.2",
												"ease": "easeoutsine",
												"destroy-on-complete": "no",
												"loop": "no",
												"ping-pong": "no",
												"repeat-count": "1"
											}
										},
										{
											"id": "wait-for-previous-actions",
											"objectClass": "System",
											"sid": 944228524164923
										},
										{
											"id": "set-layer-visible",
											"objectClass": "System",
											"sid": 957754894104642,
											"parameters": {
												"layer": "\"quit confirm\"",
												"visibility": "invisible"
											}
										}
									],
									"sid": 743386857153419
								}
							]
						}
					],
					"sid": 898303683980424,
					"text-color": [
						0,
						0,
						0,
						0
					],
					"background-color": [
						0.8392156862745098,
						0.8392156862745098,
						0.8392156862745098,
						1
					]
				},
				{
					"eventType": "group",
					"disabled": false,
					"title": "main settings",
					"description": "",
					"isActiveOnStart": true,
					"children": [
						{
							"eventType": "comment",
							"text": "when ANY button that has the section \"mainSettings\" is selected...",
							"text-color": [
								0,
								0,
								0,
								1
							],
							"background-color": [
								0.6431372549019608,
								0.8470588235294118,
								0.8745098039215686,
								1
							]
						},
						{
							"aceType": "action",
							"aceName": "uiSelect",
							"objectClass": "uiMainSettingsButton",
							"functionDescription": "overwrite the default behavior",
							"functionCategory": "ui",
							"functionReturnType": "none",
							"functionCopyPicked": false,
							"functionIsAsync": false,
							"functionParameters": [],
							"eventType": "custom-ace-block",
							"conditions": [],
							"actions": [
								{
									"type": "comment",
									"text": "call the default custom action so that it'll do the default action of growing but ALSO whatever else we say",
									"text-color": [
										0,
										0,
										0,
										1
									],
									"background-color": [
										0.8745098039215686,
										0.8352941176470589,
										0.6431372549019608,
										1
									]
								},
								{
									"customAction": "uiSelect",
									"objectClass": "uiMainSettingsButton",
									"customActionObjectClass": "ui",
									"sid": 195218284513436
								},
								{
									"type": "comment",
									"text": "a little tilt effect",
									"text-color": [
										0,
										0,
										0,
										1
									],
									"background-color": [
										0.8745098039215686,
										0.8352941176470589,
										0.6431372549019608,
										1
									]
								},
								{
									"id": "set-angle",
									"objectClass": "uiMainSettingsButton",
									"sid": 685526579461280,
									"parameters": {
										"angle": "choose(-5, 5)"
									}
								},
								{
									"id": "tween-one-property",
									"objectClass": "uiMainSettingsButton",
									"sid": 685918888768615,
									"behaviorType": "Tween",
									"parameters": {
										"tags": "\"tilt\"",
										"property": "offsetAngle",
										"end-value": "0",
										"time": "0.1",
										"ease": "easeoutsine",
										"destroy-on-complete": "no",
										"loop": "no",
										"ping-pong": "no",
										"repeat-count": "1"
									}
								}
							],
							"sid": 839400395796596
						},
						{
							"eventType": "comment",
							"text": "back",
							"text-color": [
								0,
								0,
								0,
								1
							],
							"background-color": [
								0.6431372549019608,
								0.8470588235294118,
								0.8745098039215686,
								1
							]
						},
						{
							"functionName": "select mainSettingsBack",
							"functionDescription": "",
							"functionCategory": "select",
							"functionReturnType": "none",
							"functionCopyPicked": true,
							"functionIsAsync": false,
							"functionParameters": [],
							"eventType": "function-block",
							"conditions": [],
							"actions": [],
							"sid": 932982672231228,
							"children": [
								{
									"eventType": "block",
									"conditions": [],
									"actions": [
										{
											"callFunction": "uiEnableSection",
											"sid": 894830298270813,
											"parameters": [
												"\"main\""
											]
										},
										{
											"callFunction": "uiDisableSection",
											"sid": 853848025532462,
											"parameters": [
												"\"mainSettings\""
											]
										},
										{
											"type": "comment",
											"text": "make the settings go back up",
											"text-color": [
												0,
												0,
												0,
												1
											],
											"background-color": [
												0.8745098039215686,
												0.8352941176470589,
												0.6431372549019608,
												1
											]
										},
										{
											"id": "stop-tweens",
											"objectClass": "uiMainSettingsBg",
											"sid": 186862562353368,
											"behaviorType": "Tween",
											"parameters": {
												"tags": "\"move\""
											}
										},
										{
											"id": "tween-one-property",
											"objectClass": "uiMainSettingsBg",
											"sid": 927198506841212,
											"behaviorType": "Tween",
											"parameters": {
												"tags": "\"move up\"",
												"property": "offsetY",
												"end-value": "Self.oY",
												"time": "0.2",
												"ease": "easeoutsine",
												"destroy-on-complete": "no",
												"loop": "no",
												"ping-pong": "no",
												"repeat-count": "1"
											}
										},
										{
											"id": "wait-for-previous-actions",
											"objectClass": "System",
											"sid": 301761219706821
										},
										{
											"id": "set-layer-visible",
											"objectClass": "System",
											"sid": 281347536658962,
											"parameters": {
												"layer": "\"settings\"",
												"visibility": "invisible"
											}
										}
									],
									"sid": 276787597068250
								}
							]
						},
						{
							"eventType": "group",
							"disabled": false,
							"title": "main settings slider handle common",
							"description": "",
							"isActiveOnStart": true,
							"children": [
								{
									"eventType": "comment",
									"text": "numbers above handles get updated on move",
									"text-color": [
										0,
										0,
										0,
										1
									],
									"background-color": [
										0.6431372549019608,
										0.8470588235294118,
										0.8745098039215686,
										1
									]
								},
								{
									"aceType": "action",
									"aceName": "uiSliderHandleMove",
									"objectClass": "uiMainSettingsSliderHandleCommon",
									"functionDescription": "",
									"functionCategory": "uiSlider",
									"functionReturnType": "none",
									"functionCopyPicked": false,
									"functionIsAsync": false,
									"functionParameters": [
										{
											"name": "x",
											"type": "number",
											"initialValue": "0",
											"comment": "",
											"sid": 622593768041568
										},
										{
											"name": "y",
											"type": "number",
											"initialValue": "0",
											"comment": "",
											"sid": 357756409713684
										}
									],
									"eventType": "custom-ace-block",
									"conditions": [],
									"actions": [
										{
											"customAction": "uiSliderHandleMove",
											"objectClass": "uiMainSettingsSliderHandleCommon",
											"customActionObjectClass": "ui",
											"sid": 963435293123226,
											"parameters": [
												"x",
												"y"
											]
										},
										{
											"type": "comment",
											"text": "careful here! I specifically put the condition to pick the child underneath as a subevent, because I want the original call above to always trigger regardless.",
											"text-color": [
												0,
												0,
												0,
												1
											],
											"background-color": [
												0.8745098039215686,
												0.8352941176470589,
												0.6431372549019608,
												1
											]
										}
									],
									"sid": 705149694022920,
									"children": [
										{
											"eventType": "block",
											"conditions": [
												{
													"id": "pick-children",
													"objectClass": "uiMainSettingsSliderHandleCommon",
													"sid": 954741150897765,
													"parameters": {
														"child": "txt",
														"which": "own"
													}
												}
											],
											"actions": [
												{
													"id": "set-text",
													"objectClass": "txt",
													"sid": 473714179196221,
													"parameters": {
														"text": "uiMainSettingsSliderHandleCommon.sliderValue"
													}
												}
											],
											"sid": 996593981831611
										}
									]
								},
								{
									"eventType": "comment",
									"text": "create glyph",
									"text-color": [
										0,
										0,
										0,
										1
									],
									"background-color": [
										0.6431372549019608,
										0.8470588235294118,
										0.8745098039215686,
										1
									]
								},
								{
									"aceType": "action",
									"aceName": "uiSliderHandleSelect",
									"objectClass": "uiMainSettingsSliderHandleCommon",
									"functionDescription": "",
									"functionCategory": "uiSlider",
									"functionReturnType": "none",
									"functionCopyPicked": false,
									"functionIsAsync": false,
									"functionParameters": [],
									"eventType": "custom-ace-block",
									"conditions": [],
									"actions": [
										{
											"customAction": "uiSliderHandleSelect",
											"objectClass": "uiMainSettingsSliderHandleCommon",
											"customActionObjectClass": "ui",
											"sid": 834883461652843
										},
										{
											"id": "create-object",
											"objectClass": "System",
											"sid": 930361276223222,
											"parameters": {
												"object-to-create": "uiMainSettingsSliderHandleGlyph",
												"layer": "\"settings\"",
												"x": "uiMainSettingsSliderHandleCommon.X",
												"y": "uiMainSettingsSliderHandleCommon.Y",
												"create-hierarchy": false,
												"template-name": "\"\""
											}
										},
										{
											"id": "add-child",
											"objectClass": "uiMainSettingsSliderHandleCommon",
											"sid": 763736890167682,
											"parameters": {
												"child": "uiMainSettingsSliderHandleGlyph",
												"transform-x": true,
												"transform-y": true,
												"transform-w": false,
												"transform-h": false,
												"transform-a": true,
												"transform-o": true,
												"transform-z-elevation": true,
												"transform-visibility": true,
												"destroy-with-parent": true
											}
										},
										{
											"id": "set-angle",
											"objectClass": "uiMainSettingsSliderHandleGlyph",
											"sid": 952961226856742,
											"parameters": {
												"angle": "uiMainSettingsSliderHandleCommon.Angle"
											}
										},
										{
											"id": "set-width",
											"objectClass": "uiMainSettingsSliderHandleGlyph",
											"sid": 198726961619361,
											"parameters": {
												"width": "0"
											}
										},
										{
											"id": "tween-one-property",
											"objectClass": "uiMainSettingsSliderHandleGlyph",
											"sid": 402610591305573,
											"behaviorType": "Tween",
											"parameters": {
												"tags": "\"grow\"",
												"property": "offsetWidth",
												"end-value": "32",
												"time": "0.1",
												"ease": "easeoutcubic",
												"destroy-on-complete": "no",
												"loop": "no",
												"ping-pong": "no",
												"repeat-count": "1"
											}
										}
									],
									"sid": 779703167175425
								},
								{
									"eventType": "comment",
									"text": "destroy glyph",
									"text-color": [
										0,
										0,
										0,
										1
									],
									"background-color": [
										0.6431372549019608,
										0.8470588235294118,
										0.8745098039215686,
										1
									]
								},
								{
									"aceType": "action",
									"aceName": "uiSliderHandleDeselect",
									"objectClass": "uiMainSettingsSliderHandleCommon",
									"functionDescription": "",
									"functionCategory": "uiSlider",
									"functionReturnType": "none",
									"functionCopyPicked": false,
									"functionIsAsync": false,
									"functionParameters": [],
									"eventType": "custom-ace-block",
									"conditions": [],
									"actions": [
										{
											"customAction": "uiSliderHandleDeselect",
											"objectClass": "uiMainSettingsSliderHandleCommon",
											"customActionObjectClass": "ui",
											"sid": 671204097452465
										}
									],
									"sid": 803598717128567,
									"children": [
										{
											"eventType": "block",
											"conditions": [
												{
													"id": "pick-children",
													"objectClass": "uiMainSettingsSliderHandleCommon",
													"sid": 773533599465884,
													"parameters": {
														"child": "uiMainSettingsSliderHandleGlyph",
														"which": "own"
													}
												}
											],
											"actions": [
												{
													"id": "stop-tweens",
													"objectClass": "uiMainSettingsSliderHandleGlyph",
													"sid": 284230501493380,
													"behaviorType": "Tween",
													"parameters": {
														"tags": "\"grow\""
													}
												},
												{
													"id": "tween-one-property",
													"objectClass": "uiMainSettingsSliderHandleGlyph",
													"sid": 941533737783675,
													"behaviorType": "Tween",
													"parameters": {
														"tags": "\"shrink\"",
														"property": "offsetWidth",
														"end-value": "0",
														"time": "0.1",
														"ease": "easeoutcubic",
														"destroy-on-complete": "yes",
														"loop": "no",
														"ping-pong": "no",
														"repeat-count": "1"
													}
												}
											],
											"sid": 559104282222225
										}
									]
								}
							],
							"sid": 672656558661624,
							"text-color": [
								0,
								0,
								0,
								0
							],
							"background-color": [
								0.8392156862745098,
								0.8392156862745098,
								0.8392156862745098,
								1
							]
						},
						{
							"eventType": "group",
							"disabled": false,
							"title": "main settings slider handle sfx",
							"description": "",
							"isActiveOnStart": true,
							"children": [
								{
									"eventType": "comment",
									"text": "set color based on value",
									"text-color": [
										0,
										0,
										0,
										1
									],
									"background-color": [
										0.6431372549019608,
										0.8470588235294118,
										0.8745098039215686,
										1
									]
								},
								{
									"aceType": "action",
									"aceName": "specialColor",
									"objectClass": "uiMainSettingsSliderHandleSFX",
									"functionDescription": "",
									"functionCategory": "",
									"functionReturnType": "none",
									"functionCopyPicked": false,
									"functionIsAsync": false,
									"functionParameters": [],
									"eventType": "custom-ace-block",
									"conditions": [],
									"actions": [
										{
											"id": "stop-tweens",
											"objectClass": "uiMainSettingsSliderHandleSFX",
											"sid": 287607505194555,
											"behaviorType": "Tween",
											"parameters": {
												"tags": "\"uiSliderHandleColor\""
											}
										},
										{
											"id": "set-default-color",
											"objectClass": "uiMainSettingsSliderHandleSFX",
											"sid": 170163097830069,
											"parameters": {
												"color": "rgbEx(lerp(100, 0, Self.sliderProgress), lerp(0, 100, Self.sliderProgress), 0)"
											}
										}
									],
									"sid": 805613306524219,
									"children": [
										{
											"eventType": "block",
											"conditions": [
												{
													"id": "pick-children",
													"objectClass": "uiMainSettingsSliderHandleSFX",
													"sid": 296569476648259,
													"parameters": {
														"child": "uiMainSettingsSliderHandleGlyph",
														"which": "own"
													}
												}
											],
											"actions": [
												{
													"id": "set-default-color",
													"objectClass": "uiMainSettingsSliderHandleGlyph",
													"sid": 370963447873049,
													"parameters": {
														"color": "uiMainSettingsSliderHandleSFX.ColorValue"
													}
												}
											],
											"sid": 195704085026886
										}
									]
								},
								{
									"eventType": "comment",
									"text": "numbers above handles get updated on move",
									"text-color": [
										0,
										0,
										0,
										1
									],
									"background-color": [
										0.6431372549019608,
										0.8470588235294118,
										0.8745098039215686,
										1
									]
								},
								{
									"aceType": "action",
									"aceName": "uiSliderHandleMove",
									"objectClass": "uiMainSettingsSliderHandleSFX",
									"functionDescription": "",
									"functionCategory": "uiSlider",
									"functionReturnType": "none",
									"functionCopyPicked": false,
									"functionIsAsync": false,
									"functionParameters": [
										{
											"name": "x",
											"type": "number",
											"initialValue": "0",
											"comment": "",
											"sid": 395353598690024
										},
										{
											"name": "y",
											"type": "number",
											"initialValue": "0",
											"comment": "",
											"sid": 743609699576973
										}
									],
									"eventType": "custom-ace-block",
									"conditions": [],
									"actions": [
										{
											"customAction": "uiSliderHandleMove",
											"objectClass": "uiMainSettingsSliderHandleSFX",
											"customActionObjectClass": "ui",
											"sid": 805685607762757,
											"parameters": [
												"x",
												"y"
											]
										},
										{
											"customAction": "specialColor",
											"objectClass": "uiMainSettingsSliderHandleSFX",
											"sid": 169443390061209
										}
									],
									"sid": 503077780473953
								},
								{
									"eventType": "comment",
									"text": "create glyph",
									"text-color": [
										0,
										0,
										0,
										1
									],
									"background-color": [
										0.6431372549019608,
										0.8470588235294118,
										0.8745098039215686,
										1
									]
								},
								{
									"aceType": "action",
									"aceName": "uiSliderHandleSelect",
									"objectClass": "uiMainSettingsSliderHandleSFX",
									"functionDescription": "",
									"functionCategory": "uiSlider",
									"functionReturnType": "none",
									"functionCopyPicked": false,
									"functionIsAsync": false,
									"functionParameters": [],
									"eventType": "custom-ace-block",
									"conditions": [],
									"actions": [
										{
											"customAction": "uiSliderHandleSelect",
											"objectClass": "uiMainSettingsSliderHandleSFX",
											"customActionObjectClass": "ui",
											"sid": 966061171694352
										},
										{
											"id": "create-object",
											"objectClass": "System",
											"sid": 581213280894325,
											"parameters": {
												"object-to-create": "uiMainSettingsSliderHandleGlyph",
												"layer": "\"settings\"",
												"x": "uiMainSettingsSliderHandleSFX.X",
												"y": "uiMainSettingsSliderHandleSFX.Y",
												"create-hierarchy": false,
												"template-name": "\"\""
											}
										},
										{
											"id": "add-child",
											"objectClass": "uiMainSettingsSliderHandleSFX",
											"sid": 999602818608761,
											"parameters": {
												"child": "uiMainSettingsSliderHandleGlyph",
												"transform-x": true,
												"transform-y": true,
												"transform-w": false,
												"transform-h": false,
												"transform-a": true,
												"transform-o": true,
												"transform-z-elevation": true,
												"transform-visibility": true,
												"destroy-with-parent": true
											}
										},
										{
											"id": "set-angle",
											"objectClass": "uiMainSettingsSliderHandleGlyph",
											"sid": 664026745517592,
											"parameters": {
												"angle": "uiMainSettingsSliderHandleSFX.Angle"
											}
										},
										{
											"id": "set-width",
											"objectClass": "uiMainSettingsSliderHandleGlyph",
											"sid": 593353153180486,
											"parameters": {
												"width": "0"
											}
										},
										{
											"id": "tween-one-property",
											"objectClass": "uiMainSettingsSliderHandleGlyph",
											"sid": 296504066353188,
											"behaviorType": "Tween",
											"parameters": {
												"tags": "\"grow\"",
												"property": "offsetWidth",
												"end-value": "32",
												"time": "0.1",
												"ease": "easeoutcubic",
												"destroy-on-complete": "no",
												"loop": "no",
												"ping-pong": "no",
												"repeat-count": "1"
											}
										},
										{
											"customAction": "specialColor",
											"objectClass": "uiMainSettingsSliderHandleSFX",
											"sid": 902932388096565
										}
									],
									"sid": 983662723979903
								},
								{
									"eventType": "comment",
									"text": "destroy glyph",
									"text-color": [
										0,
										0,
										0,
										1
									],
									"background-color": [
										0.6431372549019608,
										0.8470588235294118,
										0.8745098039215686,
										1
									]
								},
								{
									"aceType": "action",
									"aceName": "uiSliderHandleDeselect",
									"objectClass": "uiMainSettingsSliderHandleSFX",
									"functionDescription": "",
									"functionCategory": "uiSlider",
									"functionReturnType": "none",
									"functionCopyPicked": false,
									"functionIsAsync": false,
									"functionParameters": [],
									"eventType": "custom-ace-block",
									"conditions": [],
									"actions": [
										{
											"customAction": "uiSliderHandleDeselect",
											"objectClass": "uiMainSettingsSliderHandleSFX",
											"customActionObjectClass": "ui",
											"sid": 813068036639142
										}
									],
									"sid": 533972934199482,
									"children": [
										{
											"eventType": "block",
											"conditions": [
												{
													"id": "pick-children",
													"objectClass": "uiMainSettingsSliderHandleSFX",
													"sid": 281127392974294,
													"parameters": {
														"child": "uiMainSettingsSliderHandleGlyph",
														"which": "own"
													}
												}
											],
											"actions": [
												{
													"id": "stop-tweens",
													"objectClass": "uiMainSettingsSliderHandleGlyph",
													"sid": 362645775606547,
													"behaviorType": "Tween",
													"parameters": {
														"tags": "\"grow\""
													}
												},
												{
													"id": "tween-one-property",
													"objectClass": "uiMainSettingsSliderHandleGlyph",
													"sid": 887843367295737,
													"behaviorType": "Tween",
													"parameters": {
														"tags": "\"shrink\"",
														"property": "offsetWidth",
														"end-value": "0",
														"time": "0.1",
														"ease": "easeoutcubic",
														"destroy-on-complete": "yes",
														"loop": "no",
														"ping-pong": "no",
														"repeat-count": "1"
													}
												}
											],
											"sid": 986112082136579
										}
									]
								}
							],
							"sid": 642512339159715,
							"text-color": [
								0,
								0,
								0,
								0
							],
							"background-color": [
								0.8392156862745098,
								0.8392156862745098,
								0.8392156862745098,
								1
							]
						}
					],
					"sid": 446797142748565,
					"text-color": [
						0,
						0,
						0,
						0
					],
					"background-color": [
						0.8392156862745098,
						0.8392156862745098,
						0.8392156862745098,
						1
					]
				}
			],
			"sid": 308581722289132,
			"text-color": [
				0,
				0,
				0,
				0
			],
			"background-color": [
				0.8392156862745098,
				0.8392156862745098,
				0.8392156862745098,
				1
			]
		}
	],
	"sid": 297068062009297
}